{"songs": [{"title": "I\u2019ll Go", "lyrics": "And you don't stop\nAnd you don't stop\nAnd you don't stop\nAnd you don't stop\n\n[ 2X ]\n(I'll go)\nYou better keep on your jacket cause it's cold outside\n(I'll go)\nAnd I don't need you to worry that I run and hide\n(I'll go)\nBest believe me, my darling, when I tell you so\n(I'll go)\nWherever you want to take me, that's where I will go\n\n[ VERSE 1 ]\nListen to the rhyme as I kick it\nI used to think that every single woman was wicked\nI used to think that she would step to me and then do me wrong\nBecause I made some dollars from a hip-hop song\nNow I know I'm being kind of hard on them\nBut the girlies used to do me like an ATM\nWalk up smilin, move like a flash\nPush a couple of buttons and step with the cash\nSo here you come like a diamond in the rough\nTalkin sensible and not the same old stuff\nBut I was still scared and actin kinda timid\nBecause the other girlies really pushed me to the limit\nBut now I think I've had a change of heart\nBecause I feel kinda empty when we're apart\nAnd I don't wanna lose ya, so now I let you know\nWherever you want to take me I'll go\n\n[ 8X ]\n(I'll go)\nAnd you don't stop\n\n[ VERSE 2 ]\nNow I wanna say I'm sorry for everything I did\nI'm lookin like a man but I'm actin like a kid\nI wanna get witcha but still I'm movin slow\nA man is always frightened of the things he doesn't know\nBut yo, that doesn't mean that I should do you wrong\nBecause we been together for oh so long\nAnd you've been with me through thick and through thin\nSo it's about time I should let you in\nSo baby, baby, you're the light of my life\nYou're the apple of my eye, someday you might be my wife\nI wasn't bonin or hittin skins like all the rest\nBecause I been boneless and skinless like a chicken breast\nSo come with me and I'll come with you\nIt doesn't really matter, baby, what you wanna do\nI'm sayin yes to ya cause I'm sick of sayin no\nAnd wherever you want to take me I'll go\n\n[ 8X ]\n(I'll go)\nAnd you don't stop\n\n[ VERSE 3 ]\nNow if you have a little trouble choosin\nI'll tell you with the Young one you will never be losin\nAlways tell the truth, never give an excuse and\nBy the way you'll never find me smokin or boozin\nSee, I'm nothin like the men that you had before\nWith a wam-bam, thank you m'am and then snore\nI'm tellin you straight, cause that's the way that I am\nThere's a whole bunch of room between the wam and the bam\nConsequently or incidentally\nI want to love you slow and then caress you gently\nI treat you like a queen and not like a hooker\nThe other guys be illin because they think you're such a looker\nI'll be your jacket when it's cold outside\nAnd I don't need you to worry that I run and hide\nBest believe me, my darling, when I tell you so\nWherever you want to take me, that's where I will go\n\n[ 8X ]\n(I'll go)\nAnd you don't stop\n\n[ repeated until fade ]\n(I'll go)\nYou better keep on your jacket cause it's cold outside\n(I'll go)\nAnd I don't need you to worry that I run and hide\n(I'll go)\nBest believe me, my darling, when I tell you so\n(I'll go)\nWherever you want to take me, that's where I will go", "album": "What\u2019s the Flavor?", "year": null, "image": "https://images.genius.com/743fe6665da144a8348078d042110c70.600x600x1.jpg"}], "artist": "Young MC"}