{"songs": [{"title": "All I Got", "lyrics": "[Produced by: Young Chop]\n\n[Hook: Young Chop] x8\nAll I got, all I got\nThis money and music that's all I got\n\n[Verse 1: Young Chop]\nAll I got, all I got, is this fifty and this mac\nAll I got, all I got is them shooters up in the back\nAll I got, nigga wanna take my chain, that's a wrap\nAll I got, pop a nigga, young berg, I take it back\nAll I got, niggas hating on the kid\nAll I got, these bitch ass niggas picking wigs\nAll I got, y'all niggas talk a lot of shit\nAll I got, I got this thirty with this beam, ho\nI got this 4-5 with extendo\nBlow a nigga like Nintendo (Cartridges)\nI got the forty with that beam ho\n\n[Hook]\n\n[Verse 2: Fat Trel]\nAll I got, is this hunnid' clip and this mop\nAll I got, is some bitches beggin' for top\nAll I got, my True Religion pocket squad\nAll I got, Maybach Music, we make a lot\nThat's all I got, you try to take my chain it's a wrap\nWe bustin' shots, my young nigga gon' set up shop\nI'll bust a block, my migo bitch in California grow the pot\nThey askin' question like the cops, ho\nI got this chopper out the window, a Swisher filled with endo\nI blow that at your kinfolk, grrra, at your kinfolk\n\n[Hook]", "album": "Still ", "year": "2014-06-23", "image": "https://images.genius.com/653b99da20324f104c6278064d071626.1000x1000x1.jpg"}], "artist": "Young Chop"}