{"songs": [{"lyrics": "[Chorus]\nSend it up\nSend it through\nSend it, back to you\nSend it up\nSend it through\nSend it, back to you\n\n[Verse 1]\nYour inner view to me is\nSomething that I do desire\nStruggling to see a new something that I fantasize\nSo I'm sending\n\n[Chorus]\nSend it up\nSend it through\nSend it, back to you\nSend it up\nSend it through\nSend it, back to you\n\n[Verse 2]\nYou can't disguise your emotions\nYou know that I see in your eyes\nYou soul's in me, your soul's somethin that I feel inside\nRun, run, run, run, if I run Lord only knows how far that I and I\nWill fall behind\nGotta find a better place, find a better space\nSo that I, so my life may be the one reason why\n\n[Refrain]\nTell me what will I do?\nTell me what will I do\nSend it right back to you\n\n[Bridge]\nHold on be strong, for your own\nMove on before long, you'll get home\nIf you're feeling insecure\nYou can be sure, it's because\nEven if it take forever and a day for me to do\nI gotta send it on to you\n\n[Refrain]\nWhat will I do?\nTell me what will I do\n\n[Vamp]\nSend it on\nSend it right back to you\nSend it on\nSend it on\nSend it on\nWhenever you want to\nSend it on\nWhen it gets cold, babe\nSend it on\nCold outside\nSend it on\nAll your dreams\nSend it on\nWhen you get lonely\nSend it on\nWe all get lonely sometimes\nSend it on\nPick up the phone\nSend it on\nIn the morning\nSend it on\nOr in the evening\nSend it on\nAnd in the midnight hours\nSend it on\nYeah, baby\nSend it on\nYou can send it on, baby\nSend it on\nWhenever you're in need, babe\nSend it on\nWhenever you're in need\nSend it on\nJust call me baby\nSend it on\nSend on by-by baby\nSend it on\nSometime it make me want to stop and say\nSometime\nSometime\nWe don't know what else to say, but\nAnd it's alright, it's alright babe\nSo you know baby, we gotta get on\n\n[Outro]\nWhat will I do?\nTell me what will I do\nSend it on back to you\nSend it right back to you", "album": "Voodoo", "year": "2000-01-25", "title": "Send It On", "image": "https://images.genius.com/1e995f90d031a40f8d7fc4c9c8094a4d.460x460x1.jpg"}], "artist": "D\u2019Angelo"}