{"artist": "Peewee Longway", "songs": [{"album": "Mr. Blue Benjamin", "title": "Cost To Be Me", "image": "https://images.genius.com/3c35598e5643a1aa6719367645d189e1.400x400x1.jpg", "lyrics": "[Pre-Hook]\nShe asked me how a young nigga came wit them bands and drugs make you live this good\nShe asked me why a young nigga name in these streets and why a nigga keep it so hood\nShe ain't never seen a nigga like me around the club\nAnd she want to get it understood\nShe heard bitches ain't bossing\nWanna live real good, want a young nigga to take her out the hood\n\n[Hook x4]\nIt cost to be a nigga like me\nIt cost to be a boss living good\n\n[Verse 1 - PeeWee Longway]\nIt cost to be a nigga like me\nIt cost to be a boss living good\nBuilt my bitch a house in the loft in the woods\nBitch dating a boss and he keep it so hood\nFrosty so frosty I love it when she do it\nOpen like boxes she catch the jug jug\nLongway so slaucy and I put that on hood\nTrappin a benz and a check just like Nike\nBoy get yo bitch, what you mean she don't like me?\nShe ain't never seen a nigga like me\nCruisin a fristol with stupid ass watches\nFlippin a brick just like stuck in hibachi\nYou don't get to fall, lose it like me\nTake a bitch roll two burnt doobies like me\nSkeet on her titties, too freaky for Wee\nI get the picture, she feeling you Wee\nYeah it cost to be a nigga like me\nEven imposters can't duplicate me\nSmoke like a rasta when I roll OG\nChicken shrimp pasta when me and my los feast\nEven a mark monster acknowledge me\nCause it cost to be a boss nigga like me\nI run a trap house just 7 days a week\nIt really cost to be a nigga like me\nLongway\n\n[Pre-Hook]\n\n[Hook x4]\n\n[Verse 2 - PeeWee Longway]\nI ain't never seen a nigga like me waiting from her like the meno thought I told you that I'm servin lean\nFuck a nigga mean? He can never be me\nHe juggin the bricks and I'm juggin OG\nDifference between me and you my g, I'm from out the bricks and you from out the suburbs\nI just fuck and duck ya bitch and you just try to love her\nLet her in my mansion she tried to fuck without a rubber\nYou are too different my brotha\nI really wish you was my nigga, like no one other\nPlease be my distance\nBitch I'm a boss and I'm fuckin wit 50\nIt cost to be a real deal boss ass nigga\nColossal living, you hoes just gold diggers\nPass on bands, I got more I got more\nIt ain't no pressure on this cash\nShe upper echelon, living so fabulous\nThrow it in the backseat, don't look at the tag\nShe so exclusive, she neck back the jag\nMy bitch from Bermuda, she know that she bad\nLook on your computer, Longway the hashtag\nAudi A7, it came with a hatchback\nI keep it too hood and still fucked the nack nack\nI come out them trenches slangin 80 crack\nLongway\n\n[Pre-Hook]\n\n[Hook x4]", "year": null}]}