{"songs": [{"title": "Oxymoron", "album": "I\u2019m the Rapper He\u2019s the Producer", "year": "2018-02-02", "image": "https://images.genius.com/e02e0d1b818b340ffbd9be3650e346f1.1000x1000x1.jpg", "lyrics": "[Intro]\nKid Classic\nNoisy\nAy, check me out, check me out, check me out, ah\n\n[Verse 1]\nDebbie be the rapper (rapper, rapper)\nClass be the producer (producer, producer)\nAnd we ain't ever worried about an issue, why\nHe done droppin' shit to shoot ya\nEverything tastes super\nSuper good smoke and the ruler to the tutor\nIf you wanna be the ruler, then you bitches gotta come and see the boss, King Koopa\nBitch I been a boss, get my stashies\nFuck the freeway, take the back street (back street)\nI be getting head in the back seat (back seat)\nRunning up my bread like a track meet (track meet)\nWe and my team trying be rich (be rich)\nYou and yo team tryna seem rich (seem rich)\nDebbie been the girl, I don't been a bowl\nI been on the wave so long, gotten sea sick\n\n[Chorus]\nAll I ever know is to get it, get it go\nGet it, got it, get some mo\nWe ain't with it, if it's slow, oh, no, no, no\nWatch us flip it then it grow\nWe been buildin' from the floor\nI go hard at any hoe, oh\nAll I ever know is to get it, get it go\nGet it, got it, get some mo\nWe ain't with it, if it's slow, oh, no, no, no\nWatch us flip it then it grow\nWe been buildin' from the floor\nI go hard at any hoe, oh\n\n[Interlude]\nGet to killing bitches, what the business is\n\n[Verse 2]\nClass the producer (producer)\nAnd Debbie the rapper (rapper)\nBitches be mad my life like a movie and they just an actor (actor)\nOscar to the nominees to the wannabes\nDay I'm out of style is the day you find me out of tree"}], "artist": "Lil Debbie"}