{"songs": [{"image": "https://images.genius.com/ba0dc44c36145879b25adb96f974225a.1000x1000x1.jpg", "year": "2017-06-26", "title": "FIND ME (Intro)", "album": "XXXTENTACION Presents: Members Only, Vol. 3", "lyrics": "[Verse]\nWhere were you again?\nSomewhere with a friend\nWhile I was in my head\nI'm lost again, again\nShe turned around and said\nThat I was like the rest\nThat I don't understand the way it is, to her\n\n[Chorus]\nWhere were you again?\nWhere were you again?\nWhere were you again?\nWhere were you again?\n\n[Verse]\nWhere were you again?\nSomewhere with a friend\nWhile I was in my head\nI'm lost again, again\nShe turned around and said\nThat I was like the rest\nThat I don't understand the way it is, to her\n\n[Chorus]\nWhere were you again?\nWhere were you again?\nWhere were you again?\nWhere were you again?"}], "artist": "XXXTENTACION"}