{"artist": "Iggy Azalea", "songs": [{"title": "Haze (Demo)", "lyrics": "[Verse 1]\nI been caught up in you and the things you doin'\nAnd I can't lie to ya, I don't even mind\nI been tryna get used to how fast life been movin'\nAnd looking for somethin' outside this money to call mine\nTell me, tell me, tell me baby could you be that?\nThey say love is like a drug\nBaby you gon' make me relapse\nI got short comings and flaws\nBut you see me and never see that\nAnd that's what got me tryin' to be everywhere that you be at\n\n[Chorus]\nI'm in a haze\nAnd I love it\nNot just a phase\nThis is how I do\nI'm in a haze\nAnd I love it\nGot no regrets\nThis is what I wanna do\nWhat I wanna do\n\nWhat I wanna do...\n\n[Verse 2]\nI'm not tryna rush you into nothin'\nBut I don't wanna waste my time either babe\nCause no matter what\nWe can't get the time back\nSo let's not be fightin' crazy every time I see you\nLook, ain't no games with me baby\nThat ain't what I'm into\nLots of baggage 'round us\nFuck what both of us done been through\nShort comings and flaws yeah, we got em\nBut don't see those\nHonestly baby, who needs those?\n\n[Chorus]\nI'm in a haze\nAnd I love it\nNot just a phase\nThis is how I do\nI'm in a haze\nAnd I love it\nGot no regrets\nThis is what I wanna do\nWhat I wanna do\n\nWhat I wanna do...\n\n[Bridge]\nLong as you know that it's timeless\nI'll play it cold like the ice in my necklace\nGot a big ego, I'm not tryna hide it\nI'm a pretty pony\nBut boy can you ride it?\nYou caught me red handed\nBoy you know, love it when you get candid\nGetting turned on with ya in the backseat\nDown the streets like royalty\n\n[Chorus]\nI'm in a haze\nAnd I love it\nNot just a phase\nThis is how I do\nI'm in a haze\nAnd I love it\nGot no regrets\nThis is what I wanna do\n\nWhat I wanna do...\n\nI'm in a haze\nAnd I love it\nNot just a phase\nThis is how I do\nI'm in a haze\nAnd I love it\nGot no regrets\nThis is what I wanna do\n\nWhat I wanna do...", "image": "https://images.genius.com/a5c16badc65ae40f6034b0d404bab2c9.1000x1000x1.png", "album": "Digital Distortion [Shelved]", "year": "2017-02-10"}]}