{"songs": [{"title": "Ain\u2019t Fair", "album": null, "year": "2016-03-03", "image": "https://images.genius.com/2ce3a8319fdd4cc1eb0bcbbc358890b6.994x992x1.png", "lyrics": "[Intro: Lil Yachty]\nI'ma call it clean\nUh Fleacoo you snapped on this beat\nShawty said that I'm a playa, yeah\nShawty said that I'm a playa, yeah\nOk, yeah\n\n[Verse 1: Lil Yachty]\nShawty said that I'm a playa\nLil Yachty, I\u2019m the mayor\n96 for the M6, catch a nigga in the ballet\nTrust me, I know it ain\u2019t fair\nRed heads on the scene, counting cream\nRich enough to buy a new spleen\nNutted in your baby mama, now you talking to her like the ho is Billie Jean\nYou bust your gun in the air\nI aim right below your hair\nHollow shells in the nine\nDumped a clip into his spine\nCall me Yachty Columbine\nCause I'm out here causing crime\nI don't abide by your rhymes\n\n[Verse 2: Nessly]\nBitch I'm with Lil Yachty\nYou know we looking for the thotties\nIf a nigga got a problem\nWe gon' go and shoot his party\nLet this gun go retarded\nNigga look at what you started\nI don't give no passes, piece on ad-libs, nigga this shit is not [?]\nDan Marino with the plays\nBallin' like I play for the A's\nAll this cash, got our own maids\nMy main bitch not even faves\nNiggas flossed up, acting bossed up\nAsk and they don't spill [?]\nIf I fuck her got to get some money, nigga that's just the way I was raised\nKnow that they said it before\nI will not play with these hoes\nShawty I need all your dough\nDon't make me kick in your door\nShawty be talking too much\nI got a dick for her throat\nI designer my bridges\nI don't designer red bitches\n\n[Verse 3: Lil Yachty]\nI only designer myself\nMy gang, my brothers, my mama, my belt\nYachty coming for the belt\nLean dark like welts\nGreen light, we on go\nGreen dot for my bro\nBig dick for your ho\nBitch you know it's Lil Boat\nAll you lame niggas jokes, I hope ya'll have strokes\nYou niggas really lame\n36 for the chain\n38 to his brain\nAll you lil niggas lame\nYou know I had to change the game\nBitch it's Yachty, I'm insane\nRun it up, we'll take your chain"}], "artist": "Lil Yachty"}