{"songs": [{"image": "https://images.genius.com/d7cb8616465549cc89d5e8bfc9ba7e99.640x640x1.jpg", "year": "2018-08-31", "lyrics": "Songtekst van Sevn Alias \u2013 \"Migos\"\n\n[Hook]\nIk heb je bitch geskipt, zij voelt mij, maar ik heb geen tijd meer voor ho's\nIk ben in contact met cash, het roept mij, money en ik zijn amigo's\nIk heb die diamonds on me dancing, dat doet je denken aan Migos\nJij was niet met me toen ik broke, was jij bent niet met als ik glow (bitch)\n\n[Verse 1]\nSkip die bitches (exit)\nAlias ik ben waar (cash is)\nPull up in m'n trinna (trapfit)\nIk pak drie keer 10K (hattrick)\nNak je saaf en ik vertrek, eet van je taart, net alsof het je bday bash is (dom)\nWe poppen batra's geen mollie, niet schrikken als ik je zeg dat ik die M tik\nIn het veld voor die millies als Memphis\nBen fris, ik heb ijs op me, geen vriezer (jij ballt niet)\nIk hoor dat jij praat over vliegen (da's dom)\nHaal je uit de lucht als een keeper (ah)\nIk ben aan de beurt ga niet liegen\nYoung nigger, die mannen zijn oud, hi\u00ebrogliefen (ah)\nValt er money te verdienen, geen twijfel, ik kom met plezier op visite\n\n[Hook]\nIk heb je bitch geskipt, zij voelt mij maar ik heb geen tijd meer voor ho's\nIk ben in contact met cash het roept mij money en ik zijn amigo's\nIk heb die diamonds on me dancing dat doet je denken aan Migos\nJij was niet met me toen ik broke was jij bent niet met als ik glow (bitch)\n\n[Bridge]\nWeed smoke (weed smoke)\nIk ben high net vier hoog (vier hoog)\nPinkgame dom, m'n chaingame dom, doet je denken aan Migos (denken aan Migos)\nJe bitch wil ons, money en mij, want wij zijn amigo's (wij zijn amigo's)\nMaar ze krijgt niks, zij wordt geskipt, die dingen gaan niet zo (nee die dingen gaan-)\n\n[Verse 2]\nGrind ben op dat, maar ik skate niet\nEet goed, toch swag ik vies als een placemat (ugh)\nJij doet je best voor die bitch, blowt je saaf, en de rest van de maand heb je geen cash (dom)\nBitches die maken m'n hoofd af en toe moe, maar niet meer dan dat ik heb geen stress (nee)\nJe bitch in m'n phone ze laat mij niet alone, ey, zij wilt me bangen als twee straps\n\n[Hook]\nIk heb je bitch geskipt, zij voelt mij maar ik heb geen tijd meer voor ho's\nIk ben in contact met cash het roept mij money en ik zijn amigo's\nIk heb die diamonds on me dancing dat doet je denken aan Migos\nJij was niet met me toen ik broke was jij bent niet met als ik glow\nIk heb je bitch geskipt, zij voelt mij maar ik heb geen tijd meer voor ho's\nIk ben in contact met cash het roept mij money en ik zijn amigo's\nIk heb die diamonds on me dancing dat doet je denken aan Migos\nJij was niet met me toen ik broke was jij bent niet met als ik glow (bitch)\nIk heb je bitch geskipt, zij voelt mij maar ik heb geen tijd meer voor ho's\nIk ben in contact met cash het roept mij money en ik zijn amigo's\nIk heb die diamonds on me dancing dat doet je denken aan Migos\nJij was niet met me toen ik broke was jij bent niet met als ik glow (bitch)", "title": "Migos", "album": "RECASSO"}], "artist": "Sevn Alias"}