{"artist": "Kokane", "songs": [{"image": "https://images.genius.com/e73eb27a7600d8b4d7ea7d1adf27e6ec.1000x1000x1.png", "title": "No Pain No Gain", "year": "1994-04-12", "album": "Funk Upon a Rhyme", "lyrics": "No pain no gain\nI can see clearly out my window\nI'm just sitting here, remembering the good bets I took\nThat we used to go through\n(Boo hoo, you know what I mean)\nWe have friends and enemies that pass our way\nBut I think Lord\n(I think Lord)\nI think Lord will you let me breath another day?\n(Let me breath another day)\n\nI'm just sitting here\nLooking through the windows of my mind\nOf what we used to go through\nThe good and bad times\nSo now I'm down on my knees, begging you\nPlease, don't reap what I sow\nCause Lord I just want\nCause Lord I just want\nTo see my little children grow\n\nSo, no pain no gain\nI can see clearly out my window\nI'm just sitting here, remembering the times\nThat we used to go through\nWe have friends and enemies that come my way\nBut I think Lord\n(I think Lord)\nWill you let me breath another day?\n\nNow I'm true to myself\nWhich makes me feel so fine\nBut Lord I can't help to think of all the wrong things I did\nI'm gonna be in time\nSo why can't we sing a different so..., sing a different song\nCause Lord it makes me upset\nTo see one of my friends here\nAnd the next day they are gone\n\nNo pain no gain\nI can see clearly out my window\nI'm just sitting here, remembering the good bets I took\nThat we used to go through\n(Boo hoo, you know what I mean)\nWe have friends and enemies that pass our way\nBut I think Lord\n(I think Lord)\nI think Lord will you let me breath another day?\n(Let me breath another day)\n\nSo, no pain no gain\nI can see clearly out my window\nI'm just sitting here, remembering the times\nThat we used to go through\nWe have friends and enemies that come my way\nBut I think Lord\n(I think Lord)\nWill you let me breath another day?"}]}