{"songs": [{"image": "https://images.genius.com/d55bdf533057e65a2697dc571f4a13fb.320x320x1.jpg", "year": "2017-07-21", "lyrics": "Come on put your hands together\u2026\n\nWoo\u2026thank you Jesus!\n\nCome on put your hands together\u2026\n\nWoo\u2026thank you Jesus!\n\nPraise the Lord, God the Lord is our savior\n\nBeen out all night long\nAnd when you sit down beside Him, you\u2019ll get a contact high off of the fumes", "title": "Church Organ Needs Maintenance", "album": "The Good Book Vol. 2"}], "artist": "The Alchemist"}